README.md
pyproject.toml
setup.cfg
setup.py
cli/__init__.py
cli/blocks.py
cli/delete.py
cli/gridsearch.py
cli/info.py
cli/interface.py
cli/list.py
cli/makegrid.py
cli/optimize.py
cli/parse.py
cli/partitioncds.py
cli/plot_gridsearch.py
cli/plot_windows.py
cli/preprocess.py
cli/query.py
cli/simulate.py
cli/tally.py
cli/windows.py
gimble.egg-info/PKG-INFO
gimble.egg-info/SOURCES.txt
gimble.egg-info/dependency_links.txt
gimble.egg-info/entry_points.txt
gimble.egg-info/requires.txt
gimble.egg-info/top_level.txt
lib/__init__.py
lib/gimble.py
lib/optimize.py
lib/runargs.py
lib/simulate.py