Metadata-Version: 2.1
Name: gimble
Version: 1.1.0
Summary: A genome-wide IM blockwise likelihood estimation toolkit
Home-page: https://github.com/LohseLab/gIMble
Author: Lohse Lab
Author-email: gertjanbisschop@gmail.com
License: GNU GPLv3+
Project-URL: Github, https://github.com/LohseLab/gIMble
Platform: UNKNOWN
Classifier: Programming Language :: Python :: 3
Requires-Python: >=3.8
